{
  "platform": "instagram_portrait \u2014 PORT-v2 \u2014 1080\u00d71350",
  "version": "PORT-v2",
  "design": "Split Hero v3.2",
  "canvas": {
    "width": 1080,
    "height": 1350
  },
  "date": "2026-05-18",
  "reference": "pc1 (with photo + posmap)",
  "measured_zones": {
    "split_hero": {
      "x": 0,
      "y": 0,
      "width": 1080,
      "height": 560
    },
    "photo_panel": {
      "x": 0,
      "y": 0,
      "width": 560,
      "height": 560
    },
    "info_panel": {
      "x": 560,
      "y": 0,
      "width": 520,
      "height": 560
    },
    "ovr_block": {
      "x": 586,
      "y": 53,
      "width": 472,
      "height": 76
    },
    "meta_list": {
      "x": 586,
      "y": 184,
      "width": 472,
      "height": 120
    },
    "info_spacer": {
      "x": 586,
      "y": 304,
      "width": 472,
      "height": 80
    },
    "posmap_inline": {
      "x": 586,
      "y": 384,
      "width": 472,
      "height": 138
    },
    "skills_zone": {
      "x": 0,
      "y": 560,
      "width": 1080,
      "height": 790
    },
    "col_left": {
      "x": 10,
      "y": 571,
      "width": 480,
      "height": 769
    },
    "col_mid": {
      "x": 500,
      "y": 571,
      "width": 260,
      "height": 769
    },
    "col_right": {
      "x": 770,
      "y": 571,
      "width": 300,
      "height": 769
    }
  },
  "invariants": {
    "split_hero_h": 560,
    "photo_panel_w": 560,
    "posmap_inline_h": 138,
    "skills_zone_h": 790,
    "total_skill_rows": 44,
    "row_height_uniform": true,
    "row_height_variation": 0,
    "row_height_sample": [
      32,
      32,
      32,
      32,
      32
    ],
    "info_spacer_h": 80
  },
  "no_posmap_scenario": {
    "posmap_inline_present": false,
    "info_spacer_h": 240
  }
}